zolfa/nd2reader/__init__.py
zolfa/nd2reader/artificial.py
zolfa/nd2reader/common.py
zolfa/nd2reader/common_raw_metadata.py
zolfa/nd2reader/exceptions.py
zolfa/nd2reader/label_map.py
zolfa/nd2reader/legacy.py
zolfa/nd2reader/parser.py
zolfa/nd2reader/raw_metadata.py
zolfa/nd2reader/reader.py
zolfa/nd2reader/stitched.py
zolfa/nd2reader/version.py
zolfa_nd2reader-3.4.1.dist-info/COPYING
zolfa_nd2reader-3.4.1.dist-info/LICENSE
zolfa_nd2reader-3.4.1.dist-info/METADATA
zolfa_nd2reader-3.4.1.dist-info/WHEEL
zolfa_nd2reader-3.4.1.dist-info/top_level.txt
zolfa_nd2reader-3.4.1.dist-info/RECORD
