Metadata-Version: 2.1
Name: zolfa-nd2reader
Version: 3.4.1
Summary: A tool for reading ND2 files produced by NIS Elements
Author-email: Ruben Verweij <ruben@lighthacking.nl>, Lorenzo Zolfanelli <lorenzo.zolfanelli@espci.psl.eu>
Maintainer-email: Lorenzo Zolfanelli <lorenzo.zolfanelli@espci.psl.eu>
Classifier: Development Status :: 4 - Beta
Classifier: License :: OSI Approved :: GNU General Public License v3 (GPLv3)
Classifier: Intended Audience :: Science/Research
Classifier: Topic :: Scientific/Engineering :: Image Processing
Classifier: Programming Language :: Python :: 3
Classifier: Programming Language :: Python :: 3.10
Classifier: Programming Language :: Python :: 3.11
Classifier: Programming Language :: Python :: 3.12
License-File: LICENSE
License-File: COPYING
Requires-Dist: numpy >=1.14
Requires-Dist: xmltodict >=0.9.2
Requires-Dist: PIMS >=0.5.0
Provides-Extra: test
Requires-Dist: pytest ; extra == 'test'
